bsb_plotting.py
bsb_plotting-0.0.0b0.dist-info/LICENSE
bsb_plotting-0.0.0b0.dist-info/WHEEL
bsb_plotting-0.0.0b0.dist-info/METADATA
bsb_plotting-0.0.0b0.dist-info/RECORD
