Metadata-Version: 2.1
Name: bsb-plotting
Version: 0.0.0b0
Summary: Plotly-based plotting tools for the BSB framework.
Author-email: Robin De Schepper <robingilbert.deschepper@unipv.it>
Classifier: License :: OSI Approved :: GNU General Public License v3 or later (GPLv3+)
Requires-Dist: bsb-core>=4.0.0b0,<=4.0.0b9999
